README.md
setup.cfg
setup.py
whatap/LICENSE
whatap/README.rst
whatap/__init__.py
whatap/__main__.py
whatap/build.py
whatap/whatap.conf
whatap/agent/darwin/amd64/whatap_python
whatap/agent/darwin/arm64/whatap_python
whatap/agent/linux/amd64/whatap_python
whatap/agent/linux/arm64/whatap_python
whatap/agent/windows/whatap_python.exe
whatap/bootstrap/__init__.py
whatap/bootstrap/sitecustomize.py
whatap/conf/__init__.py
whatap/conf/configuration.py
whatap/conf/configure.py
whatap/conf/license.py
whatap/control/__init__.py
whatap/counter/__init__.py
whatap/counter/counter_manager.py
whatap/counter/tasks/__init__.py
whatap/counter/tasks/llm_stat.py
whatap/counter/tasks/openfiledescriptor.py
whatap/io/__init__.py
whatap/io/data_inputx.py
whatap/io/data_outputx.py
whatap/net/__init__.py
whatap/net/async_sender.py
whatap/net/packet_enum.py
whatap/net/packet_type_enum.py
whatap/net/param_def.py
whatap/net/stackhelper.py
whatap/net/udp_session.py
whatap/net/udp_thread.py
whatap/pack/__init__.py
whatap/pack/logSinkPack.py
whatap/pack/pack.py
whatap/pack/pack_enum.py
whatap/pack/tagCountPack.py
whatap/scripts/__init__.py
whatap/trace/__init__.py
whatap/trace/simple_trace_context.py
whatap/trace/trace_context.py
whatap/trace/trace_context_manager.py
whatap/trace/trace_import.py
whatap/trace/trace_module_definition.py
whatap/trace/mod/__init__.py
whatap/trace/mod/logging.py
whatap/trace/mod/plugin.py
whatap/trace/mod/amqp/__init__.py
whatap/trace/mod/amqp/kombu.py
whatap/trace/mod/amqp/pika.py
whatap/trace/mod/application/__init__.py
whatap/trace/mod/application/bottle.py
whatap/trace/mod/application/celery.py
whatap/trace/mod/application/cherrypy.py
whatap/trace/mod/application/django.py
whatap/trace/mod/application/django_asgi.py
whatap/trace/mod/application/django_py3.py
whatap/trace/mod/application/fastapi.py
whatap/trace/mod/application/flask.py
whatap/trace/mod/application/frappe.py
whatap/trace/mod/application/graphql.py
whatap/trace/mod/application/nameko.py
whatap_python.egg-info/PKG-INFO
whatap_python.egg-info/SOURCES.txt
whatap_python.egg-info/dependency_links.txt
whatap_python.egg-info/entry_points.txt
whatap_python.egg-info/not-zip-safe
whatap_python.egg-info/requires.txt
whatap_python.egg-info/top_level.txt